<?xml version="1.0" encoding="utf-8"?>
<ArrayOfLineStation xmlns:xsi="http://www.w3.org/2001/XMLSchema-instance" xmlns:xsd="http://www.w3.org/2001/XMLSchema">
	<LineStation>
		<LineId>1</LineId>
		<Station>1</Station>
		<LineStationIndex>0</LineStationIndex>
		<NextStation>2</NextStation>
		<Active>true</Active>
	</LineStation>

	<LineStation>
		<LineId>1</LineId>
		<Station>2</Station>
		<LineStationIndex>1</LineStationIndex>
		<PrevStation>1</PrevStation>
		<NextStation>3</NextStation>
		<Active>true</Active>
	</LineStation>

	<LineStation>
		<LineId>1</LineId>
		<Station>3</Station>
		<LineStationIndex>2</LineStationIndex>
		<PrevStation>2</PrevStation>
		<NextStation>4</NextStation>
		<Active>true</Active>
	</LineStation>

	<LineStation>
		<LineId>1</LineId>
		<Station>4</Station>
		<LineStationIndex>3</LineStationIndex>
		<PrevStation>3</PrevStation>
		<NextStation>5</NextStation>
		<Active>true</Active>
	</LineStation>

	<LineStation>
		<LineId>1</LineId>
		<Station>5</Station>
		<LineStationIndex>4</LineStationIndex>
		<PrevStation>4</PrevStation>
		<NextStation>6</NextStation>
		<Active>true</Active>
	</LineStation>

	<LineStation>
		<LineId>1</LineId>
		<Station>6</Station>
		<LineStationIndex>5</LineStationIndex>
		<PrevStation>5</PrevStation>
		<NextStation>7</NextStation>
		<Active>true</Active>
	</LineStation>

	<LineStation>
		<LineId>1</LineId>
		<Station>7</Station>
		<LineStationIndex>6</LineStationIndex>
		<PrevStation>6</PrevStation>
		<NextStation>8</NextStation>
		<Active>true</Active>
	</LineStation>

	<LineStation>
		<LineId>1</LineId>
		<Station>8</Station>
		<LineStationIndex>7</LineStationIndex>
		<PrevStation>7</PrevStation>
		<NextStation>9</NextStation>
		<Active>true</Active>
	</LineStation>

	<LineStation>
		<LineId>1</LineId>
		<Station>9</Station>
		<LineStationIndex>8</LineStationIndex>
		<PrevStation>8</PrevStation>
		<NextStation>10</NextStation>
		<Active>true</Active>
	</LineStation>

	<LineStation>
		<LineId>1</LineId>
		<Station>10</Station>
		<LineStationIndex>9</LineStationIndex>
		<PrevStation>9</PrevStation>
		<Active>true</Active>
	</LineStation>

	<LineStation>
		<LineId>2</LineId>
		<Station>11</Station>
		<LineStationIndex>0</LineStationIndex>
		<NextStation>12</NextStation>
		<Active>true</Active>
	</LineStation>

	<LineStation>
		<LineId>2</LineId>
		<Station>12</Station>
		<LineStationIndex>1</LineStationIndex>
		<PrevStation>11</PrevStation>
		<NextStation>13</NextStation>
		<Active>true</Active>
	</LineStation>

	<LineStation>
		<LineId>2</LineId>
		<Station>13</Station>
		<LineStationIndex>2</LineStationIndex>
		<PrevStation>12</PrevStation>
		<NextStation>14</NextStation>
		<Active>true</Active>
	</LineStation>

	<LineStation>
		<LineId>2</LineId>
		<Station>14</Station>
		<LineStationIndex>3</LineStationIndex>
		<PrevStation>13</PrevStation>
		<NextStation>15</NextStation>
		<Active>true</Active>
	</LineStation>

	<LineStation>
		<LineId>2</LineId>
		<Station>15</Station>
		<LineStationIndex>4</LineStationIndex>
		<PrevStation>14</PrevStation>
		<NextStation>16</NextStation>
		<Active>true</Active>
	</LineStation>

	<LineStation>
		<LineId>2</LineId>
		<Station>16</Station>
		<LineStationIndex>5</LineStationIndex>
		<PrevStation>15</PrevStation>
		<NextStation>17</NextStation>
		<Active>true</Active>
	</LineStation>

	<LineStation>
		<LineId>2</LineId>
		<Station>17</Station>
		<LineStationIndex>6</LineStationIndex>
		<PrevStation>16</PrevStation>
		<NextStation>18</NextStation>
		<Active>true</Active>
	</LineStation>

	<LineStation>
		<LineId>2</LineId>
		<Station>18</Station>
		<LineStationIndex>7</LineStationIndex>
		<PrevStation>17</PrevStation>
		<NextStation>19</NextStation>
		<Active>true</Active>
	</LineStation>

	<LineStation>
		<LineId>2</LineId>
		<Station>19</Station>
		<LineStationIndex>8</LineStationIndex>
		<PrevStation>18</PrevStation>
		<NextStation>20</NextStation>
		<Active>true</Active>
	</LineStation>

	<LineStation>
		<LineId>2</LineId>
		<Station>20</Station>
		<LineStationIndex>9</LineStationIndex>
		<PrevStation>19</PrevStation>
		<Active>true</Active>
	</LineStation>

	<LineStation>
		<LineId>3</LineId>
		<Station>21</Station>
		<LineStationIndex>0</LineStationIndex>
		<NextStation>22</NextStation>
		<Active>true</Active>
	</LineStation>

	<LineStation>
		<LineId>3</LineId>
		<Station>22</Station>
		<LineStationIndex>1</LineStationIndex>
		<PrevStation>21</PrevStation>
		<NextStation>23</NextStation>
		<Active>true</Active>
	</LineStation>

	<LineStation>
		<LineId>3</LineId>
		<Station>23</Station>
		<LineStationIndex>2</LineStationIndex>
		<PrevStation>22</PrevStation>
		<NextStation>24</NextStation>
		<Active>true</Active>
	</LineStation>

	<LineStation>
		<LineId>3</LineId>
		<Station>24</Station>
		<LineStationIndex>3</LineStationIndex>
		<PrevStation>23</PrevStation>
		<NextStation>25</NextStation>
		<Active>true</Active>
	</LineStation>

	<LineStation>
		<LineId>3</LineId>
		<Station>25</Station>
		<LineStationIndex>4</LineStationIndex>
		<PrevStation>24</PrevStation>
		<NextStation>26</NextStation>
		<Active>true</Active>
	</LineStation>

	<LineStation>
		<LineId>3</LineId>
		<Station>26</Station>
		<LineStationIndex>5</LineStationIndex>
		<PrevStation>25</PrevStation>
		<NextStation>27</NextStation>
		<Active>true</Active>
	</LineStation>

	<LineStation>
		<LineId>3</LineId>
		<Station>27</Station>
		<LineStationIndex>6</LineStationIndex>
		<PrevStation>26</PrevStation>
		<NextStation>28</NextStation>
		<Active>true</Active>
	</LineStation>

	<LineStation>
		<LineId>3</LineId>
		<Station>28</Station>
		<LineStationIndex>7</LineStationIndex>
		<PrevStation>27</PrevStation>
		<NextStation>29</NextStation>
		<Active>true</Active>
	</LineStation>

	<LineStation>
		<LineId>3</LineId>
		<Station>29</Station>
		<LineStationIndex>8</LineStationIndex>
		<PrevStation>28</PrevStation>
		<NextStation>30</NextStation>
		<Active>true</Active>
	</LineStation>

	<LineStation>
		<LineId>3</LineId>
		<Station>30</Station>
		<LineStationIndex>9</LineStationIndex>
		<PrevStation>29</PrevStation>
		<Active>true</Active>
	</LineStation>

	<LineStation>
		<LineId>4</LineId>
		<Station>31</Station>
		<LineStationIndex>0</LineStationIndex>
		<NextStation>32</NextStation>
		<Active>true</Active>
	</LineStation>

	<LineStation>
		<LineId>4</LineId>
		<Station>32</Station>
		<LineStationIndex>1</LineStationIndex>
		<PrevStation>31</PrevStation>
		<NextStation>33</NextStation>
		<Active>true</Active>
	</LineStation>

	<LineStation>
		<LineId>4</LineId>
		<Station>33</Station>
		<LineStationIndex>2</LineStationIndex>
		<PrevStation>32</PrevStation>
		<NextStation>34</NextStation>
		<Active>true</Active>
	</LineStation>

	<LineStation>
		<LineId>4</LineId>
		<Station>34</Station>
		<LineStationIndex>3</LineStationIndex>
		<PrevStation>33</PrevStation>
		<NextStation>35</NextStation>
		<Active>true</Active>
	</LineStation>

	<LineStation>
		<LineId>4</LineId>
		<Station>35</Station>
		<LineStationIndex>4</LineStationIndex>
		<PrevStation>34</PrevStation>
		<NextStation>36</NextStation>
		<Active>true</Active>
	</LineStation>

	<LineStation>
		<LineId>4</LineId>
		<Station>36</Station>
		<LineStationIndex>5</LineStationIndex>
		<PrevStation>35</PrevStation>
		<NextStation>37</NextStation>
		<Active>true</Active>
	</LineStation>

	<LineStation>
		<LineId>4</LineId>
		<Station>37</Station>
		<LineStationIndex>6</LineStationIndex>
		<PrevStation>36</PrevStation>
		<NextStation>38</NextStation>
		<Active>true</Active>
	</LineStation>

	<LineStation>
		<LineId>4</LineId>
		<Station>38</Station>
		<LineStationIndex>7</LineStationIndex>
		<PrevStation>37</PrevStation>
		<NextStation>39</NextStation>
		<Active>true</Active>
	</LineStation>

	<LineStation>
		<LineId>4</LineId>
		<Station>39</Station>
		<LineStationIndex>8</LineStationIndex>
		<PrevStation>38</PrevStation>
		<NextStation>40</NextStation>
		<Active>true</Active>
	</LineStation>

	<LineStation>
		<LineId>4</LineId>
		<Station>40</Station>
		<LineStationIndex>9</LineStationIndex>
		<PrevStation>39</PrevStation>
		<Active>true</Active>
	</LineStation>

	<LineStation>
		<LineId>5</LineId>
		<Station>41</Station>
		<LineStationIndex>0</LineStationIndex>
		<NextStation>42</NextStation>
		<Active>true</Active>
	</LineStation>

	<LineStation>
		<LineId>5</LineId>
		<Station>42</Station>
		<LineStationIndex>1</LineStationIndex>
		<PrevStation>41</PrevStation>
		<NextStation>43</NextStation>
		<Active>true</Active>
	</LineStation>

	<LineStation>
		<LineId>5</LineId>
		<Station>43</Station>
		<LineStationIndex>2</LineStationIndex>
		<PrevStation>42</PrevStation>
		<NextStation>44</NextStation>
		<Active>true</Active>
	</LineStation>

	<LineStation>
		<LineId>5</LineId>
		<Station>44</Station>
		<LineStationIndex>3</LineStationIndex>
		<PrevStation>43</PrevStation>
		<NextStation>45</NextStation>
		<Active>true</Active>
	</LineStation>

	<LineStation>
		<LineId>5</LineId>
		<Station>45</Station>
		<LineStationIndex>4</LineStationIndex>
		<PrevStation>44</PrevStation>
		<NextStation>46</NextStation>
		<Active>true</Active>
	</LineStation>

	<LineStation>
		<LineId>5</LineId>
		<Station>46</Station>
		<LineStationIndex>5</LineStationIndex>
		<PrevStation>45</PrevStation>
		<NextStation>47</NextStation>
		<Active>true</Active>
	</LineStation>

	<LineStation>
		<LineId>5</LineId>
		<Station>47</Station>
		<LineStationIndex>6</LineStationIndex>
		<PrevStation>46</PrevStation>
		<NextStation>48</NextStation>
		<Active>true</Active>
	</LineStation>

	<LineStation>
		<LineId>5</LineId>
		<Station>48</Station>
		<LineStationIndex>7</LineStationIndex>
		<PrevStation>47</PrevStation>
		<NextStation>49</NextStation>
		<Active>true</Active>
	</LineStation>

	<LineStation>
		<LineId>5</LineId>
		<Station>49</Station>
		<LineStationIndex>8</LineStationIndex>
		<PrevStation>48</PrevStation>
		<NextStation>50</NextStation>
		<Active>true</Active>
	</LineStation>

	<LineStation>
		<LineId>5</LineId>
		<Station>50</Station>
		<LineStationIndex>9</LineStationIndex>
		<PrevStation>49</PrevStation>
		<Active>true</Active>
	</LineStation>

	<LineStation>
		<LineId>6</LineId>
		<Station>15</Station>
		<LineStationIndex>0</LineStationIndex>
		<NextStation>16</NextStation>
		<Active>true</Active>
	</LineStation>

	<LineStation>
		<LineId>6</LineId>
		<Station>16</Station>
		<LineStationIndex>1</LineStationIndex>
		<PrevStation>15</PrevStation>
		<NextStation>17</NextStation>
		<Active>true</Active>
	</LineStation>

	<LineStation>
		<LineId>6</LineId>
		<Station>17</Station>
		<LineStationIndex>2</LineStationIndex>
		<PrevStation>16</PrevStation>
		<NextStation>18</NextStation>
		<Active>true</Active>
	</LineStation>

	<LineStation>
		<LineId>6</LineId>
		<Station>18</Station>
		<LineStationIndex>3</LineStationIndex>
		<PrevStation>17</PrevStation>
		<NextStation>19</NextStation>
		<Active>true</Active>
	</LineStation>

	<LineStation>
		<LineId>6</LineId>
		<Station>19</Station>
		<LineStationIndex>4</LineStationIndex>
		<PrevStation>18</PrevStation>
		<NextStation>20</NextStation>
		<Active>true</Active>
	</LineStation>

	<LineStation>
		<LineId>6</LineId>
		<Station>20</Station>
		<LineStationIndex>5</LineStationIndex>
		<PrevStation>19</PrevStation>
		<NextStation>21</NextStation>
		<Active>true</Active>
	</LineStation>

	<LineStation>
		<LineId>6</LineId>
		<Station>21</Station>
		<LineStationIndex>6</LineStationIndex>
		<PrevStation>20</PrevStation>
		<NextStation>22</NextStation>
		<Active>true</Active>
	</LineStation>

	<LineStation>
		<LineId>6</LineId>
		<Station>22</Station>
		<LineStationIndex>7</LineStationIndex>
		<PrevStation>21</PrevStation>
		<NextStation>23</NextStation>
		<Active>true</Active>
	</LineStation>

	<LineStation>
		<LineId>6</LineId>
		<Station>23</Station>
		<LineStationIndex>8</LineStationIndex>
		<PrevStation>22</PrevStation>
		<NextStation>24</NextStation>
		<Active>true</Active>
	</LineStation>

	<LineStation>
		<LineId>6</LineId>
		<Station>24</Station>
		<LineStationIndex>9</LineStationIndex>
		<PrevStation>23</PrevStation>
		<Active>true</Active>
	</LineStation>

	<LineStation>
		<LineId>7</LineId>
		<Station>25</Station>
		<LineStationIndex>0</LineStationIndex>
		<NextStation>26</NextStation>
		<Active>true</Active>
	</LineStation>

	<LineStation>
		<LineId>7</LineId>
		<Station>26</Station>
		<LineStationIndex>1</LineStationIndex>
		<PrevStation>25</PrevStation>
		<NextStation>27</NextStation>
		<Active>true</Active>
	</LineStation>

	<LineStation>
		<LineId>7</LineId>
		<Station>27</Station>
		<LineStationIndex>2</LineStationIndex>
		<PrevStation>26</PrevStation>
		<NextStation>28</NextStation>
		<Active>true</Active>
	</LineStation>

	<LineStation>
		<LineId>7</LineId>
		<Station>28</Station>
		<LineStationIndex>3</LineStationIndex>
		<PrevStation>27</PrevStation>
		<NextStation>29</NextStation>
		<Active>true</Active>
	</LineStation>

	<LineStation>
		<LineId>7</LineId>
		<Station>29</Station>
		<LineStationIndex>4</LineStationIndex>
		<PrevStation>28</PrevStation>
		<NextStation>30</NextStation>
		<Active>true</Active>
	</LineStation>

	<LineStation>
		<LineId>7</LineId>
		<Station>30</Station>
		<LineStationIndex>5</LineStationIndex>
		<PrevStation>29</PrevStation>
		<NextStation>31</NextStation>
		<Active>true</Active>
	</LineStation>

	<LineStation>
		<LineId>7</LineId>
		<Station>31</Station>
		<LineStationIndex>6</LineStationIndex>
		<PrevStation>30</PrevStation>
		<NextStation>32</NextStation>
		<Active>true</Active>
	</LineStation>

	<LineStation>
		<LineId>7</LineId>
		<Station>32</Station>
		<LineStationIndex>7</LineStationIndex>
		<PrevStation>31</PrevStation>
		<NextStation>33</NextStation>
		<Active>true</Active>
	</LineStation>

	<LineStation>
		<LineId>7</LineId>
		<Station>33</Station>
		<LineStationIndex>8</LineStationIndex>
		<PrevStation>32</PrevStation>
		<NextStation>34</NextStation>
		<Active>true</Active>
	</LineStation>

	<LineStation>
		<LineId>7</LineId>
		<Station>34</Station>
		<LineStationIndex>9</LineStationIndex>
		<PrevStation>33</PrevStation>
		<Active>true</Active>
	</LineStation>

	<LineStation>
		<LineId>8</LineId>
		<Station>35</Station>
		<LineStationIndex>0</LineStationIndex>
		<NextStation>36</NextStation>
		<Active>true</Active>
	</LineStation>

	<LineStation>
		<LineId>8</LineId>
		<Station>36</Station>
		<LineStationIndex>1</LineStationIndex>
		<PrevStation>35</PrevStation>
		<NextStation>37</NextStation>
		<Active>true</Active>
	</LineStation>

	<LineStation>
		<LineId>8</LineId>
		<Station>37</Station>
		<LineStationIndex>2</LineStationIndex>
		<PrevStation>36</PrevStation>
		<NextStation>38</NextStation>
		<Active>true</Active>
	</LineStation>

	<LineStation>
		<LineId>8</LineId>
		<Station>38</Station>
		<LineStationIndex>3</LineStationIndex>
		<PrevStation>37</PrevStation>
		<NextStation>39</NextStation>
		<Active>true</Active>
	</LineStation>

	<LineStation>
		<LineId>8</LineId>
		<Station>39</Station>
		<LineStationIndex>4</LineStationIndex>
		<PrevStation>38</PrevStation>
		<NextStation>40</NextStation>
		<Active>true</Active>
	</LineStation>

	<LineStation>
		<LineId>8</LineId>
		<Station>40</Station>
		<LineStationIndex>5</LineStationIndex>
		<PrevStation>39</PrevStation>
		<NextStation>41</NextStation>
		<Active>true</Active>
	</LineStation>

	<LineStation>
		<LineId>8</LineId>
		<Station>41</Station>
		<LineStationIndex>6</LineStationIndex>
		<PrevStation>40</PrevStation>
		<NextStation>42</NextStation>
		<Active>true</Active>
	</LineStation>

	<LineStation>
		<LineId>8</LineId>
		<Station>42</Station>
		<LineStationIndex>7</LineStationIndex>
		<PrevStation>41</PrevStation>
		<NextStation>43</NextStation>
		<Active>true</Active>
	</LineStation>

	<LineStation>
		<LineId>8</LineId>
		<Station>43</Station>
		<LineStationIndex>8</LineStationIndex>
		<PrevStation>42</PrevStation>
		<NextStation>44</NextStation>
		<Active>true</Active>
	</LineStation>

	<LineStation>
		<LineId>8</LineId>
		<Station>44</Station>
		<LineStationIndex>9</LineStationIndex>
		<PrevStation>43</PrevStation>
		<Active>true</Active>
	</LineStation>

	<LineStation>
		<LineId>9</LineId>
		<Station>45</Station>
		<LineStationIndex>0</LineStationIndex>
		<NextStation>46</NextStation>
		<Active>true</Active>
	</LineStation>

	<LineStation>
		<LineId>9</LineId>
		<Station>46</Station>
		<LineStationIndex>1</LineStationIndex>
		<PrevStation>45</PrevStation>
		<NextStation>47</NextStation>
		<Active>true</Active>
	</LineStation>

	<LineStation>
		<LineId>9</LineId>
		<Station>47</Station>
		<LineStationIndex>2</LineStationIndex>
		<PrevStation>46</PrevStation>
		<NextStation>48</NextStation>
		<Active>true</Active>
	</LineStation>

	<LineStation>
		<LineId>9</LineId>
		<Station>48</Station>
		<LineStationIndex>3</LineStationIndex>
		<PrevStation>47</PrevStation>
		<NextStation>49</NextStation>
		<Active>true</Active>
	</LineStation>

	<LineStation>
		<LineId>9</LineId>
		<Station>49</Station>
		<LineStationIndex>4</LineStationIndex>
		<PrevStation>48</PrevStation>
		<NextStation>50</NextStation>
		<Active>true</Active>
	</LineStation>

	<LineStation>
		<LineId>9</LineId>
		<Station>50</Station>
		<LineStationIndex>5</LineStationIndex>
		<PrevStation>49</PrevStation>
		<NextStation>51</NextStation>
		<Active>true</Active>
	</LineStation>

	<LineStation>
		<LineId>9</LineId>
		<Station>51</Station>
		<LineStationIndex>6</LineStationIndex>
		<PrevStation>50</PrevStation>
		<NextStation>52</NextStation>
		<Active>true</Active>
	</LineStation>

	<LineStation>
		<LineId>9</LineId>
		<Station>52</Station>
		<LineStationIndex>7</LineStationIndex>
		<PrevStation>51</PrevStation>
		<NextStation>53</NextStation>
		<Active>true</Active>
	</LineStation>

	<LineStation>
		<LineId>9</LineId>
		<Station>53</Station>
		<LineStationIndex>8</LineStationIndex>
		<PrevStation>52</PrevStation>
		<NextStation>54</NextStation>
		<Active>true</Active>
	</LineStation>

	<LineStation>
		<LineId>9</LineId>
		<Station>54</Station>
		<LineStationIndex>9</LineStationIndex>
		<PrevStation>53</PrevStation>
		<Active>true</Active>
	</LineStation>

	<LineStation>
		<LineId>10</LineId>
		<Station>20</Station>
		<LineStationIndex>0</LineStationIndex>
		<NextStation>21</NextStation>
		<Active>true</Active>
	</LineStation>

	<LineStation>
		<LineId>10</LineId>
		<Station>21</Station>
		<LineStationIndex>1</LineStationIndex>
		<PrevStation>20</PrevStation>
		<NextStation>22</NextStation>
		<Active>true</Active>
	</LineStation>

	<LineStation>
		<LineId>10</LineId>
		<Station>22</Station>
		<LineStationIndex>2</LineStationIndex>
		<PrevStation>21</PrevStation>
		<NextStation>23</NextStation>
		<Active>true</Active>
	</LineStation>

	<LineStation>
		<LineId>10</LineId>
		<Station>23</Station>
		<LineStationIndex>3</LineStationIndex>
		<PrevStation>22</PrevStation>
		<NextStation>24</NextStation>
		<Active>true</Active>
	</LineStation>

	<LineStation>
		<LineId>10</LineId>
		<Station>24</Station>
		<LineStationIndex>4</LineStationIndex>
		<PrevStation>23</PrevStation>
		<NextStation>25</NextStation>
		<Active>true</Active>
	</LineStation>

	<LineStation>
		<LineId>10</LineId>
		<Station>25</Station>
		<LineStationIndex>5</LineStationIndex>
		<PrevStation>24</PrevStation>
		<NextStation>26</NextStation>
		<Active>true</Active>
	</LineStation>

	<LineStation>
		<LineId>10</LineId>
		<Station>26</Station>
		<LineStationIndex>6</LineStationIndex>
		<PrevStation>25</PrevStation>
		<NextStation>27</NextStation>
		<Active>true</Active>
	</LineStation>

	<LineStation>
		<LineId>10</LineId>
		<Station>27</Station>
		<LineStationIndex>7</LineStationIndex>
		<PrevStation>26</PrevStation>
		<NextStation>28</NextStation>
		<Active>true</Active>
	</LineStation>

	<LineStation>
		<LineId>10</LineId>
		<Station>28</Station>
		<LineStationIndex>8</LineStationIndex>
		<PrevStation>27</PrevStation>
		<NextStation>29</NextStation>
		<Active>true</Active>
	</LineStation>

	<LineStation>
		<LineId>10</LineId>
		<Station>29</Station>
		<LineStationIndex>9</LineStationIndex>
		<PrevStation>28</PrevStation>
		<NextStation>30</NextStation>
		<Active>true</Active>
	</LineStation>

	<LineStation>
		<LineId>10</LineId>
		<Station>30</Station>
		<LineStationIndex>10</LineStationIndex>
		<PrevStation>29</PrevStation>
		<NextStation>31</NextStation>
		<Active>true</Active>
	</LineStation>

	<LineStation>
		<LineId>10</LineId>
		<Station>31</Station>
		<LineStationIndex>11</LineStationIndex>
		<PrevStation>30</PrevStation>
		<NextStation>32</NextStation>
		<Active>true</Active>
	</LineStation>

	<LineStation>
		<LineId>10</LineId>
		<Station>32</Station>
		<LineStationIndex>12</LineStationIndex>
		<PrevStation>31</PrevStation>
		<NextStation>33</NextStation>
		<Active>true</Active>
	</LineStation>

	<LineStation>
		<LineId>10</LineId>
		<Station>33</Station>
		<LineStationIndex>13</LineStationIndex>
		<PrevStation>32</PrevStation>
		<NextStation>34</NextStation>
		<Active>true</Active>
	</LineStation>

	<LineStation>
		<LineId>10</LineId>
		<Station>34</Station>
		<LineStationIndex>14</LineStationIndex>
		<PrevStation>33</PrevStation>
		<NextStation>35</NextStation>
		<Active>true</Active>
	</LineStation>

	<LineStation>
		<LineId>10</LineId>
		<Station>35</Station>
		<LineStationIndex>15</LineStationIndex>
		<PrevStation>34</PrevStation>
		<NextStation>36</NextStation>
		<Active>true</Active>
	</LineStation>

	<LineStation>
		<LineId>10</LineId>
		<Station>36</Station>
		<LineStationIndex>16</LineStationIndex>
		<PrevStation>35</PrevStation>
		<NextStation>37</NextStation>
		<Active>true</Active>
	</LineStation>

	<LineStation>
		<LineId>10</LineId>
		<Station>37</Station>
		<LineStationIndex>17</LineStationIndex>
		<PrevStation>36</PrevStation>
		<NextStation>38</NextStation>
		<Active>true</Active>
	</LineStation>

	<LineStation>
		<LineId>10</LineId>
		<Station>38</Station>
		<LineStationIndex>18</LineStationIndex>
		<PrevStation>37</PrevStation>
		<NextStation>39</NextStation>
		<Active>true</Active>
	</LineStation>

	<LineStation>
		<LineId>10</LineId>
		<Station>39</Station>
		<LineStationIndex>19</LineStationIndex>
		<PrevStation>38</PrevStation>
		<Active>true</Active>
	</LineStation>

	Press any key to continue . . .
</ArrayOfLineStation>